morph/__init__.py
morph/action.py
morph/base.py
morph/examples.py
morph/index.py
morph/json_serializer.py
morph/message.py
morph/response.py
morph/test.py
morph/utils.py
morph/variable.py
morph_ai-1.0.8.dist-info/LICENSE.txt
morph_ai-1.0.8.dist-info/METADATA
morph_ai-1.0.8.dist-info/WHEEL
morph_ai-1.0.8.dist-info/top_level.txt
morph_ai-1.0.8.dist-info/RECORD
