Metadata-Version: 2.1
Name: morph-ai
Version: 1.0.8
Summary: Morph.ai Custom code SDK for python
Home-page: https://github.com/scupid-admin/morph-python-sdk
Author: Ishan Jain
Author-email: ishan@morph.ai
License: UNKNOWN
Download-URL: https://github.com/scupid-admin/morph-python-sdk/archive/1.0.0.tar.gz
Keywords: chatbots,custom code,morph.ai
Platform: UNKNOWN
